dtr_common/__init__.py
dtr_common/constantes.py
dtr_common/retry.py
dtr_common/utils.py
dtr_common/exceptions/__init__.py
dtr_common/exceptions/errors.py
dtr_common/exceptions/handlers.py
dtr_common/ftp/__init__.py
dtr_common/ftp/ftp_util.py
dtr_common/ftp/ftps.py
dtr_common/logs/__init__.py
dtr_common/logs/formatter.py
dtr_common/logs/logger.py
dtr_common/protocols/__init__.py
dtr_common/protocols/base.py
dtr_common/protocols/ftps.py
dtr_common/protocols/s3.py
dtr_common/protocols/sftp.py
dtr_common/types/__init__.py
dtr_common/types/configuration.py
dtr_common/types/filter.py
dtr_common/types/models.py
dtr_common/types/requests.py
dtr_common/types/response.py
dtr_common-1.0.2.dist-info/METADATA
dtr_common-1.0.2.dist-info/WHEEL
dtr_common-1.0.2.dist-info/top_level.txt
dtr_common-1.0.2.dist-info/RECORD
